{"dataName":"card100189","Name":{"id":"100189","str":"【SSR】ダクネス[クルセイダーシールド]"},"CharaID":{"id":"11003","str":"ダクネス"},"NickName":"クルセイダーシールド","SortOrder":"4030010","Attribute":"Leaf","School":{"id":"22","str":"この素晴らしい世界に祝福を！2"},"NameForCommonModel":null,"IsCommonModel":"false","IsDigital":"false","IsTicketUsable":"true","CardEffect":{"IsEffect":"false","EffectID":"0"},"Gakunen":{"id":"0","str":"-"},"PersonalityIDs":null,"Rarity":"SSR","LevelParam":{"int":["55","252","275","290","302","312","0","0","0","317"]},"SkillID":{"id":"100144","str":"アタック +13"},"ChoKaikaSkillID":{"id":"100145","str":"アタック +15"},"CardRightsName":{"id":"18","str":"©2017 暁なつめ・三嶋くろね／ＫＡＤＯＫＡＷＡ／このすば２製作委員会"},"VersionID":{"id":"1005","str":"ver_1_05"},"CardNumberString":"[O.N.G.E.K.I.]1.05-E-0057","LicenseID":{"id":"8","str":"この素晴らしい世界に祝福を！2（リバイバル）"},"IsLockedAtTheBeginning":"false","PrintEndDateTime":"2021-07-07T00:00:00"}