{"dataName":"card100528","Name":{"id":"100528","str":"【SR】箱根 彩耶[雪月花]"},"CharaID":{"id":"25001","str":"草津 結衣奈"},"NickName":"雪月花","SortOrder":"9022010","Attribute":"Aqua","School":{"id":"29","str":"温泉むすめ"},"NameForCommonModel":"箱根 彩耶","IsCommonModel":"true","IsDigital":"false","IsTicketUsable":"true","CardEffect":{"IsEffect":"false","EffectID":"0"},"Gakunen":{"id":"0","str":"-"},"PersonalityIDs":null,"Rarity":"SR","LevelParam":{"int":["50","222","237","252","267","282","0","0","0","282"]},"SkillID":{"id":"110094","str":"アタック +10（追撃 +2）"},"ChoKaikaSkillID":{"id":"110095","str":"アタック +12（追撃 +2）"},"CardRightsName":{"id":"48","str":"© 温泉むすめ／Enbound, Inc."},"VersionID":{"id":"1010","str":"ver_1_10"},"CardNumberString":"[O.N.G.E.K.I.]1.10-E-0052","LicenseID":{"id":"13","str":"温泉むすめ"},"IsLockedAtTheBeginning":"false","PrintEndDateTime":"2022-08-03T00:00:00"}