{"dataName":"card100627","Name":{"id":"100627","str":"【SSR】古明地 こいし[本能「イドの解放」]"},"CharaID":{"id":"2021","str":"古明地 こいし"},"NickName":"本能「イドの解放」","SortOrder":"1210010","Attribute":"Fire","School":{"id":"17","str":"東方Project　古明地姉妹編"},"NameForCommonModel":null,"IsCommonModel":"false","IsDigital":"false","IsTicketUsable":"true","CardEffect":{"IsEffect":"false","EffectID":"0"},"Gakunen":{"id":"0","str":"-"},"PersonalityIDs":null,"Rarity":"SSR","LevelParam":{"int":["60","265","286","299","309","317","0","0","0","322"]},"SkillID":{"id":"100036","str":"アタック +15"},"ChoKaikaSkillID":{"id":"100077","str":"アタック +17"},"CardRightsName":{"id":"1","str":"©上海アリス幻樂団"},"VersionID":{"id":"1020","str":"ver_1_20"},"CardNumberString":"[O.N.G.E.K.I.]1.20-E-0076","LicenseID":{"id":"1","str":"東方Project"},"IsLockedAtTheBeginning":"false","PrintEndDateTime":"0001-01-01T00:00:00"}