{"dataName":"card101041","Name":{"id":"101041","str":"【SR】洩矢 諏訪子[土着神の頂点]"},"CharaID":{"id":"2023","str":"洩矢 諏訪子"},"NickName":"土着神の頂点","SortOrder":"1232010","Attribute":"Leaf","School":{"id":"45","str":"東方Project　早苗＆諏訪子編"},"NameForCommonModel":null,"IsCommonModel":"false","IsDigital":"false","IsTicketUsable":"true","CardEffect":{"IsEffect":"false","EffectID":"0"},"Gakunen":{"id":"0","str":"-"},"PersonalityIDs":null,"Rarity":"SR","LevelParam":{"int":["50","222","237","252","267","282","0","0","0","282"]},"SkillID":{"id":"100025","str":"アタック +11"},"ChoKaikaSkillID":{"id":"100066","str":"アタック +13"},"CardRightsName":{"id":"1","str":"©上海アリス幻樂団"},"VersionID":{"id":"1025","str":"ver_1_25"},"CardNumberString":"[O.N.G.E.K.I.]1.25-E-0200","LicenseID":{"id":"1","str":"東方Project"},"IsLockedAtTheBeginning":"false","PrintEndDateTime":"0001-01-01T00:00:00"}