{"dataName":"card101128","Name":{"id":"101128","str":"【SR】月坂 紗由[PJs:PARTY!!]"},"CharaID":{"id":"32001","str":"式宮 舞菜"},"NickName":"PJs:PARTY!!","SortOrder":"18022020","Attribute":"Leaf","School":{"id":"37","str":"Re:ステージ！プリズムステップ"},"NameForCommonModel":"月坂 紗由","IsCommonModel":"true","IsDigital":"false","IsTicketUsable":"true","CardEffect":{"IsEffect":"false","EffectID":"0"},"Gakunen":{"id":"0","str":"-"},"PersonalityIDs":null,"Rarity":"SR","LevelParam":{"int":["50","222","237","252","267","282","0","0","0","282"]},"SkillID":{"id":"110094","str":"アタック +10（追撃 +2）"},"ChoKaikaSkillID":{"id":"110095","str":"アタック +12（追撃 +2）"},"CardRightsName":{"id":"65","str":"© Re:STAGE! PROJECT"},"VersionID":{"id":"1020","str":"ver_1_20"},"CardNumberString":"[O.N.G.E.K.I.]1.20-E-0132","LicenseID":{"id":"31","str":"Re:ステージ！プリズムステップ（第2弾）"},"IsLockedAtTheBeginning":"false","PrintEndDateTime":"0001-01-01T00:00:00"}