{"dataName":"udemaeSeasonReward200602","name":{"id":"200602","str":"シーズン6ポイント報酬_2"},"seasonId":{"id":"2006","str":"オトモダチ対戦シーズン6"},"rewardKind":"Point","rewardParam":"200","itemType":"MusicNew","PartnerId":{"id":"1","str":"でらっくま"},"CharacterId":{"id":"101","str":"でらっくま"},"MusicId":{"id":"1081","str":"サンバランド"},"TitleId":{"id":"1","str":"でびゅー"},"PlateId":{"id":"1","str":"デフォルト"},"IconId":{"id":"1","str":"デフォルト"},"FrameId":{"id":"1","str":"デフォルト"},"TicketId":{"id":"0","str":"使用しない"},"itemId":{"id":"1081","str":"サンバランド"}}