{"dataName":"udemaeSeasonReward201301","name":{"id":"201301","str":"シーズン13ポイント報酬_1"},"seasonId":{"id":"2013","str":"オトモダチ対戦シーズン13"},"rewardKind":"Point","rewardParam":"100","itemType":"MusicNew","PartnerId":{"id":"1","str":"でらっくま"},"CharacterId":{"id":"101","str":"でらっくま"},"MusicId":{"id":"10251","str":"Monochrome Rainbow"},"TitleId":{"id":"1","str":"でびゅー"},"PlateId":{"id":"1","str":"デフォルト"},"IconId":{"id":"1","str":"デフォルト"},"FrameId":{"id":"1","str":"デフォルト"},"TicketId":{"id":"0","str":"使用しない"},"itemId":{"id":"10251","str":"Monochrome Rainbow"}}