{"dataName":"trophy020039","Name":{"id":"20039","str":"Gate of Doom"},"Disabled":"false","PossessingFromTheBeginning":"false","IsLockedAtTheBeginning":"false","TrophyRarityType":"Platinum","Description":"Gate of Doom\n/全難易度/FULLBELL/ALLBREAK","SortOrder":"251550","TrophyConditionType":"HighScoreReference","TrophyCondition":{"@xsi:type":"TrophyConditionHighScore","TrophyConditionType":"None","MusicIDs":{"MusicStringID":{"id":"39","str":"Gate of Doom","Value":{"id":"39","str":"Gate of Doom"}}},"FumenDifficultyFlag":{"Basic":"true","Advanced":"true","Expert":"true","Master":"true","Lunatic":"false"},"HighScoreFlag":{"Play":"false","Retire":"false","Completion":"false","Win":"false","FullCombo":"false","AllBreak":"true","FullBell":"true","NoDamage":"false"},"TechnicalRank":"None","BattleRank":"None"}}