{"dataName":"trophy020157","Name":{"id":"20157","str":"TeA"},"Disabled":"false","PossessingFromTheBeginning":"false","IsLockedAtTheBeginning":"false","TrophyRarityType":"Platinum","Description":"TeA\n/全難易度/FULLBELL/ALLBREAK","SortOrder":"261200","TrophyConditionType":"HighScoreReference","TrophyCondition":{"@xsi:type":"TrophyConditionHighScore","TrophyConditionType":"None","MusicIDs":{"MusicStringID":{"id":"157","str":"TeA","Value":{"id":"157","str":"TeA"}}},"FumenDifficultyFlag":{"Basic":"true","Advanced":"true","Expert":"true","Master":"true","Lunatic":"false"},"HighScoreFlag":{"Play":"false","Retire":"false","Completion":"false","Win":"false","FullCombo":"false","AllBreak":"true","FullBell":"true","NoDamage":"false"},"TechnicalRank":"None","BattleRank":"None"}}