{"dataName":"trophy020227","Name":{"id":"20227","str":"寒想桜"},"Disabled":"false","PossessingFromTheBeginning":"false","IsLockedAtTheBeginning":"false","TrophyRarityType":"Platinum","Description":"寒想桜\n/全難易度/FULLBELL/ALLBREAK","SortOrder":"230480","TrophyConditionType":"HighScoreReference","TrophyCondition":{"@xsi:type":"TrophyConditionHighScore","TrophyConditionType":"None","MusicIDs":{"MusicStringID":{"id":"227","str":"寒想桜","Value":{"id":"227","str":"寒想桜"}}},"FumenDifficultyFlag":{"Basic":"true","Advanced":"true","Expert":"true","Master":"true","Lunatic":"false"},"HighScoreFlag":{"Play":"false","Retire":"false","Completion":"false","Win":"false","FullCombo":"false","AllBreak":"true","FullBell":"true","NoDamage":"false"},"TechnicalRank":"None","BattleRank":"None"}}