{"dataName":"trophy020281","Name":{"id":"20281","str":"感情アクセラレイション"},"Disabled":"false","PossessingFromTheBeginning":"false","IsLockedAtTheBeginning":"false","TrophyRarityType":"Platinum","Description":"感情アクセラレイション\n/全難易度/FULLBELL/ALLBREAK","SortOrder":"261010","TrophyConditionType":"HighScoreReference","TrophyCondition":{"@xsi:type":"TrophyConditionHighScore","TrophyConditionType":"None","MusicIDs":{"MusicStringID":{"id":"281","str":"感情アクセラレイション","Value":{"id":"281","str":"感情アクセラレイション"}}},"FumenDifficultyFlag":{"Basic":"true","Advanced":"true","Expert":"true","Master":"true","Lunatic":"false"},"HighScoreFlag":{"Play":"false","Retire":"false","Completion":"false","Win":"false","FullCombo":"false","AllBreak":"true","FullBell":"true","NoDamage":"false"},"TechnicalRank":"None","BattleRank":"None"}}