{"dataName":"trophy020464","Name":{"id":"20464","str":"STORIA"},"Disabled":"false","PossessingFromTheBeginning":"false","IsLockedAtTheBeginning":"false","TrophyRarityType":"Platinum","Description":"STORIA\n/全難易度/FULLBELL/ALLBREAK","SortOrder":"211690","TrophyConditionType":"HighScoreReference","TrophyCondition":{"@xsi:type":"TrophyConditionHighScore","TrophyConditionType":"None","MusicIDs":{"MusicStringID":{"id":"466","str":"STORIA","Value":{"id":"466","str":"STORIA"}}},"FumenDifficultyFlag":{"Basic":"true","Advanced":"true","Expert":"true","Master":"true","Lunatic":"false"},"HighScoreFlag":{"Play":"false","Retire":"false","Completion":"false","Win":"false","FullCombo":"false","AllBreak":"true","FullBell":"true","NoDamage":"false"},"TechnicalRank":"None","BattleRank":"None"}}