{"dataName":"trophy033701","Name":{"id":"33701","str":"香川勢"},"Disabled":"false","PossessingFromTheBeginning":"false","IsLockedAtTheBeginning":"false","TrophyRarityType":"Normal","Description":"香川県で\nオンゲキを3TRACKプレイ","SortOrder":"303600","TrophyConditionType":"TotalStatusReference","TrophyCondition":{"@xsi:type":"TrophyConditionTotalStatus","TrophyConditionType":"None","TotalStatusConditionType":"PrefecturePlayedMusic","TrophyTotalStatusCondition_":{"@xsi:type":"TrophyTotalStatusCondition_PrefecturePlayedMusic","TotalStatusConditionType":"PrefecturePlayedMusic","ID":"Kagawa","Value":"3","Comparison":"MoreThanOrEqual"},"NecessaryPossessedCollectionType":"None"}}