{"dataName":"event1350420801","Name":{"id":"1350420801","str":"楽曲解禁：Vibes 2k20 (owl＊aging remix)"},"EventType":"UnlockMusic","Event":{"@xsi:type":"EventUnlockMusic","EventType":"UnlockMusic","MusicList":{"MusicStringID":[{"id":"785","str":"Vibes 2k20 (owl＊aging remix)","Value":{"id":"785","str":"Vibes 2k20 (owl＊aging remix)"}},{"id":"751","str":"Baqeela (Creepy Remix)","Value":{"id":"751","str":"Baqeela (Creepy Remix)"}},{"id":"763","str":"MarbleBlue.","Value":{"id":"763","str":"MarbleBlue."}},{"id":"762","str":"オンソクデイズ!!","Value":{"id":"762","str":"オンソクデイズ!!"}}]}}}