{"dataName":"mapArea02206902","netOpenName":{"id":"2430","str":"v2_20 14_1","data":null},"name":{"id":"2206902","str":"かいりき0102","data":null},"hiddenType":"0","unlockText":"-","mapBonusName":{"id":"14801","str":"かいりき_01","data":null},"mapAreaBoostType":"0","mapAreaBoostMultiple":"10","shorteningGridCountList":{"MapAreaGridShorteningData":[{"count":"0"},{"count":"0"},{"count":"0"},{"count":"0"},{"count":"0"},{"count":"0"},{"count":"0"},{"count":"0"}]},"grids":{"MapAreaGridData":[{"index":"0","displayType":"1","type":"1","exit":null,"entrance":null,"reward":{"rewardName":{"id":"-1","str":"Invalid","data":null}}},{"index":"5","displayType":"3","type":"3","exit":null,"entrance":null,"reward":{"rewardName":{"id":"10000010","str":"Point 1000","data":null}}},{"index":"15","displayType":"3","type":"3","exit":null,"entrance":null,"reward":{"rewardName":{"id":"10000010","str":"Point 1000","data":null}}},{"index":"25","displayType":"2","type":"2","exit":null,"entrance":null,"reward":{"rewardName":{"id":"-1","str":"Invalid","data":null}}}]}}