{"dataName":"cpu0701","name":{"id":"701","str":"cpu0701","data":null},"cpuLevel":"7","strength":"1","ratelow":"1430","ratehigh":"1469","spawnrate":"10","scores":{"CPUScore":[{"score":"1007200"},{"score":"1007200"},{"score":"1006000"},{"score":"1006000"},{"score":"1005000"},{"score":"1005000"},{"score":"1003000"},{"score":"1003000"},{"score":"1002000"},{"score":"1002000"},{"score":"1001000"},{"score":"1001000"},{"score":"1000000"},{"score":"1000000"},{"score":"995000"},{"score":"995000"},{"score":"990000"},{"score":"990000"},{"score":"975000"},{"score":"950000"},{"score":"900000"},{"score":"850000"},{"score":"750000"}]}}