{"dataName":"music2528","releaseTagName":{"id":"16","str":"v2 2.20.00","data":null},"netOpenName":{"id":"2401","str":"v2_20 00_1","data":null},"disableFlag":"false","exType":"0","name":{"id":"2528","str":"Blow My Mind","data":null},"sortName":"BLOWMYMIND","artistName":{"id":"2528","str":"3R2「Cytus Ⅱ」","data":null},"genreNames":{"list":{"StringID":{"id":"6","str":"VARIETY","data":null}}},"worksName":{"id":"-1","str":"Invalid","data":null},"jaketFile":{"path":"CHU_UI_Jacket_2528.dds"},"firstLock":"true","enableUltima":"false","isGiftMusic":"false","priority":"0","cueFileName":{"id":"2528","str":"music2528","data":null},"worldsEndTagName":{"id":"-1","str":"Invalid","data":null},"starDifType":"1","stageName":{"id":"10","str":"レーベル 共通0010_LUMINOUS","data":null},"fumens":{"MusicFumenData":[{"type":{"id":"0","str":"Basic","data":"BASIC"},"enable":"true","file":{"path":"2528_00.c2s"},"level":"3","levelDecimal":"0","notesDesigner":null,"defaultBpm":"0"},{"type":{"id":"1","str":"Advanced","data":"ADVANCED"},"enable":"true","file":{"path":"2528_01.c2s"},"level":"6","levelDecimal":"0","notesDesigner":null,"defaultBpm":"0"},{"type":{"id":"2","str":"Expert","data":"EXPERT"},"enable":"true","file":{"path":"2528_02.c2s"},"level":"11","levelDecimal":"80","notesDesigner":null,"defaultBpm":"0"},{"type":{"id":"3","str":"Master","data":"MASTER"},"enable":"true","file":{"path":"2528_03.c2s"},"level":"14","levelDecimal":"10","notesDesigner":null,"defaultBpm":"0"},{"type":{"id":"4","str":"Ultima","data":"ULTIMA"},"enable":"false","file":{"path":null},"level":"0","levelDecimal":"0","notesDesigner":null,"defaultBpm":"0"},{"type":{"id":"5","str":"WorldsEnd","data":"WORLD'S END"},"enable":"false","file":{"path":null},"level":"0","levelDecimal":"0","notesDesigner":null,"defaultBpm":"0"}]}}