{"dataName":"course301108","name":{"id":"301108","str":"1.30_真八段"},"courseMode":{"id":"2","str":"真段位認定"},"baseDaniId":{"id":"19","str":"真八段"},"baseCourseId":{"id":"0","str":"未使用"},"fileName":null,"isRandom":"false","upperLevel":"0","lowerLevel":"0","isLock":"true","conditionsUnlockCourse":{"id":"301010","str":"1.30_十段"},"courseMusicData":{"CourseMusicData":[{"musicId":{"id":"11384","str":"HAGAKIRI"},"difficulty":{"id":"3","str":"Master"}},{"musicId":{"id":"24","str":"Sun Dance"},"difficulty":{"id":"4","str":"ReMaster"}},{"musicId":{"id":"11425","str":"First Dance"},"difficulty":{"id":"3","str":"Master"}},{"musicId":{"id":"745","str":"keep hopping"},"difficulty":{"id":"3","str":"Master"}}]},"life":"50","recover":"10","perfectDamage":"0","greatDamage":"2","goodDamage":"3","missDamage":"5","eventId":{"id":"0","str":"解放なし"},"netOpenName":{"id":"999","str":"Net990101"}}