{"dataName":"course351010","name":{"id":"351010","str":"1.35_十段"},"courseMode":{"id":"1","str":"段位認定"},"baseDaniId":{"id":"10","str":"十段"},"baseCourseId":{"id":"0","str":"未使用"},"fileName":null,"isRandom":"false","upperLevel":"0","lowerLevel":"0","isLock":"false","conditionsUnlockCourse":{"id":"1001","str":"1.17_初段"},"courseMusicData":{"CourseMusicData":[{"musicId":{"id":"11466","str":"群青シグナル"},"difficulty":{"id":"3","str":"Master"}},{"musicId":{"id":"642","str":"Justified"},"difficulty":{"id":"3","str":"Master"}},{"musicId":{"id":"11454","str":"Tricolor⁂circuS"},"difficulty":{"id":"3","str":"Master"}},{"musicId":{"id":"379","str":"Caliburne ～Story of the Legendary sword～"},"difficulty":{"id":"3","str":"Master"}}]},"life":"900","recover":"30","perfectDamage":"0","greatDamage":"2","goodDamage":"2","missDamage":"5","eventId":{"id":"0","str":"解放なし"},"netOpenName":{"id":"230323","str":"Net230323"}}