{"dataName":"chapter003081","Name":{"id":"3081","str":"海の家で一番美味しいアレ"},"Story":{"id":"3","str":"第3章"},"Type":"SideChapter","DisplayNumber":"1","SortOrder":"10190","IsOriginalEvent":"false","IsLockedAtTheBeginning":"false","JewelGraphicName":{"id":"300","str":"第3章ジュエル"},"BackgroundName":{"id":"300301","str":"学園祭通り"},"MusicList":{"ChapterMusic":[{"MusicName":{"id":"264","str":"MAKING！ハイタッチ！"},"Condition":{"ItemType":"None","ConditionItem":{"id":"-1","str":"Invalid"},"OwnNumCondition":"1","Comparison":"MoreThanOrEqual"}},{"MusicName":{"id":"265","str":"GEOMETRIC DANCE"},"Condition":{"ItemType":"None","ConditionItem":{"id":"-1","str":"Invalid"},"OwnNumCondition":"1","Comparison":"MoreThanOrEqual"}},{"MusicName":{"id":"320","str":"インビジブル"},"Condition":{"ItemType":"None","ConditionItem":{"id":"-1","str":"Invalid"},"OwnNumCondition":"1","Comparison":"MoreThanOrEqual"}}]},"PurchaseItemList":null,"CharaList":{"ChapterChara":{"CharaID":{"id":"1011","str":"逢坂 茜"},"RequiredMusicClearedCount":"0"}}}