{"dataName":"MapBonusMusic100059","name":{"id":"100059","str":"にじさんじちほーボーナス曲"},"MusicIds":{"list":{"StringID":[{"id":"11184","str":"Virtual to LIVE"},{"id":"11348","str":"VOLTAGE"},{"id":"11430","str":"オントロジー"},{"id":"11503","str":"Baddest"},{"id":"11577","str":"はんぶんこ"},{"id":"10411","str":"初音ミクの消失"},{"id":"11578","str":"PUPA"},{"id":"11580","str":"解けないように"},{"id":"11608","str":"NOIZY BOUNCE"},{"id":"11609","str":"サンバディ！"},{"id":"11610","str":"Horoscope Express"},{"id":"11611","str":"Party☆People☆Princess"},{"id":"11624","str":"SQUAD-Phvntom-"},{"id":"11625","str":"GEOMETRIC DANCE"},{"id":"11629","str":"熱異常"},{"id":"11630","str":"1000年生きてる"},{"id":"11631","str":"IMAWANOKIWA"},{"id":"11632","str":"Play merrily NEO"},{"id":"11633","str":"OMAKENO Stroke"},{"id":"11634","str":"青春コンプレックス"},{"id":"11635","str":"アンダーキッズ"},{"id":"11636","str":"さくゆいたいそう"},{"id":"11637","str":"バグ"},{"id":"11664","str":"アルカンシエル"},{"id":"411","str":"初音ミクの消失"},{"id":"11433","str":"ヒトガタ"},{"id":"11497","str":"アマカミサマ"},{"id":"11498","str":"モンダイナイトリッパー！"},{"id":"11501","str":"Dive into the ZONe"},{"id":"11555","str":"ヒバリ"},{"id":"11556","str":"Hello, Hologram"},{"id":"11557","str":"不機嫌なスリーカード"},{"id":"11506","str":"Blank Paper (Prod. TEMPLIME)"},{"id":"11507","str":"In my world (Prod. KOTONOHOUSE)"},{"id":"11096","str":"モ°ルモ°ル"},{"id":"10363","str":"Oshama Scramble!"},{"id":"363","str":"Oshama Scramble!"},{"id":"364","str":"D✪N’T  ST✪P  R✪CKIN’"},{"id":"11007","str":"超常マイマイン"},{"id":"11152","str":"ぼくたちいつでも　しゅわっしゅわ！"},{"id":"70","str":"ジングルベル"},{"id":"10070","str":"ジングルベル"},{"id":"630","str":"曖昧mind"}]}}}