{"dataName":"chara001015","Name":{"id":"1015","str":"東雲 つむぎ"},"FirstContactRewardCardData":{"id":"100452","str":"【N】東雲 つむぎ"},"Model":{"id":"1015","str":"東雲 つむぎ"},"GraphicCardData":{"id":"100452","str":"【N】東雲 つむぎ"},"IsModelless":"false","FlavorText":"こんなところで負けません\n　　私、立派な大人ですから","FlavorText2":"冷静に油断せず……\n　　全力で行きます","FlavorText3":"子供扱いしてると\n　　痛い目見ますよ……！","FlavorText4":"準備はバッチリです\n　　たくさん練習しましたから","FlavorText5":"こっちをジロジロ見ないで下さい\n　　防犯ブザーを鳴らしますよ","FlavorText6":"え、パンケーキ！？\n　　……そ、そんなものでは\n　　　　　　　　　懐柔されません！","Birthday":"2018-10-27T00:00:00","BloodType":"A","PersonalityType":"Cool","Height":"144","Profile":{"ProfileString":[{"Profile":"テクノポップ"},{"Profile":"パンケーキ/テレビ番組"},{"Profile":"子ども扱いする人"},{"Profile":"アクアリウム"},{"Profile":"ピアノ/旅行の計画作り"},{"Profile":"日記を書くこと"},{"Profile":"水族館にお出かけ"},{"Profile":"好きなだけ夜更かしをする"},{"Profile":"大人"},{"Profile":"子どものころに縁日でとった金魚たち。一匹一匹に名前を付け、今も自宅で大切に育てている。"}]},"ProfileVoice":{"ProfileVoiceNameStringID":[{"StringID":{"id":"11501","str":"東雲 つむぎ フレーバーボイス01"}},{"StringID":{"id":"11502","str":"東雲 つむぎ フレーバーボイス02"}},{"StringID":{"id":"11503","str":"東雲 つむぎ フレーバーボイス03"}},{"StringID":{"id":"11504","str":"東雲 つむぎ フレーバーボイス04"}},{"StringID":{"id":"11505","str":"東雲 つむぎ フレーバーボイス05"}},{"StringID":{"id":"11506","str":"東雲 つむぎ フレーバーボイス06"}},{"StringID":{"id":"11507","str":"東雲 つむぎ フレーバーボイス07"}},{"StringID":{"id":"11508","str":"東雲 つむぎ フレーバーボイス08"}},{"StringID":{"id":"11509","str":"東雲 つむぎ フレーバーボイス09"}},{"StringID":{"id":"11510","str":"東雲 つむぎ フレーバーボイス10"}}]},"Trophy":{"TrophyNameStringID":[{"StringID":{"id":"11501","str":"東雲つむぎ推し"}},{"StringID":{"id":"11502","str":"子ども扱い禁止です！"}},{"StringID":{"id":"11503","str":"見た目は子ども、中身も子ども"}},{"StringID":{"id":"11504","str":"ツンツン娘の防犯ブザー担当"}},{"StringID":{"id":"11505","str":"ツンツン娘の防犯ブザー担当・80dB"}},{"StringID":{"id":"11506","str":"ツンツン娘の防犯ブザー担当・120dB"}},{"StringID":{"id":"11507","str":"背伸びっ子の成長を見守り隊"}},{"StringID":{"id":"11508","str":"東雲つむぎ推し"}},{"StringID":{"id":"11509","str":"つむぎと二人で大人の階段を"}}]},"NamePlate":{"NamePlateNameStringID":[{"StringID":{"id":"11501","str":"♥東雲 つむぎ♥"}},{"StringID":{"id":"11502","str":"♥♥♥東雲 つむぎ♥♥♥"}}]},"Attachment":{"AttachmentNameStringID":{"StringID":{"id":"2015","str":"スペシャルオーラ（東雲 つむぎ）"}}},"SortOrder":"1160","IsCommunicationTarget":"true"}