{"dataName":"music0068","Name":{"id":"68","str":"P！P！P！P！がおー!!"},"ArtistName":{"id":"41","str":"曲：Tom-H@ck／歌：結城 莉玖(CV：朝日奈 丸佳)"},"MusicRightsName":{"id":"0","str":"-"},"MusicSourceName":{"id":"68","str":"P！P！P！P！がおー!!"},"Genre":{"id":"6","str":"オンゲキ"},"FirstChapterName":{"id":"1003","str":"嘘とがおー！とかたき討ち"},"FumenData":{"FumenData":[{"FumenConstIntegerPart":"4","FumenConstFractionalPart":"0","FumenFile":{"path":"0068_00.ogkr"}},{"FumenConstIntegerPart":"7","FumenConstFractionalPart":"70","FumenFile":{"path":"0068_01.ogkr"}},{"FumenConstIntegerPart":"10","FumenConstFractionalPart":"70","FumenFile":{"path":"0068_02.ogkr"}},{"FumenConstIntegerPart":"12","FumenConstFractionalPart":"90","FumenFile":{"path":"0068_03.ogkr"}},{"FumenConstIntegerPart":"0","FumenConstFractionalPart":"0","FumenFile":{"path":null}}]},"IsLunatic":"false","BossCard":{"id":"100038","str":"【SR】結城 莉玖[嘘とがおー！とかたき討ち]"},"BossLevel":"5","WaveAttribute":{"AttributeType":"Fire"},"CostToUnlock":"0","FinishBonus":"2","EpReleaseFlag":"false","VersionID":{"id":"1000","str":"ver_1_00"},"SortOrder":"607100","StageID":{"id":"6","str":"学園_06_教室"},"PossessingFromTheBeginning":"true","IsLockedAtTheBeginning":"false","ReleaseVersion":"2018-07-26T00:00:00","NameForSort":"PPPPカオ","BossLockHpCoef":"50500","BossLockRewards":{"BossLockReward":{"RewardName":{"id":"7008095","str":"P！P！P！P！がおー!!"},"RewardCount":"1"}},"BossVoiceNo":"1","IsBonusTrack":"false"}