{"dataName":"music0282","Name":{"id":"282","str":"Desperado Waltz"},"ArtistName":{"id":"2970","str":"ぺのれり"},"MusicRightsName":{"id":"0","str":"-"},"MusicSourceName":{"id":"282","str":"Desperado Waltz"},"Genre":{"id":"6","str":"オンゲキ"},"FirstChapterName":{"id":"3001","str":"いきなりシューターフェス決勝！"},"FumenData":{"FumenData":[{"FumenConstIntegerPart":"3","FumenConstFractionalPart":"0","FumenFile":{"path":"0282_00.ogkr"}},{"FumenConstIntegerPart":"7","FumenConstFractionalPart":"70","FumenFile":{"path":"0282_01.ogkr"}},{"FumenConstIntegerPart":"12","FumenConstFractionalPart":"70","FumenFile":{"path":"0282_02.ogkr"}},{"FumenConstIntegerPart":"14","FumenConstFractionalPart":"40","FumenFile":{"path":"0282_03.ogkr"}},{"FumenConstIntegerPart":"0","FumenConstFractionalPart":"0","FumenFile":{"path":null}}]},"IsLunatic":"false","BossCard":{"id":"100444","str":"【SR+】東雲 つむぎ[いきなりシューターフェス決勝！+]"},"BossLevel":"25","WaveAttribute":{"AttributeType":"Aqua"},"CostToUnlock":"0","FinishBonus":"2","EpReleaseFlag":"false","VersionID":{"id":"1010","str":"ver_1_10"},"SortOrder":"619400","StageID":{"id":"14","str":"フェス会場"},"PossessingFromTheBeginning":"true","IsLockedAtTheBeginning":"false","ReleaseVersion":"2019-08-22T00:00:00","NameForSort":"DESPERADOWALTZ","BossLockHpCoef":"0","BossLockRewards":null,"BossVoiceNo":"1","IsBonusTrack":"false"}