{"dataName":"music0931","Name":{"id":"931","str":"星めぐり、果ての君へ。"},"ArtistName":{"id":"7110","str":"TAKU1175 ft.駄々子"},"MusicRightsName":{"id":"0","str":"-"},"MusicSourceName":{"id":"931","str":"星めぐり、果ての君へ。"},"Genre":{"id":"5","str":"チュウマイ"},"FirstChapterName":{"id":"1","str":"マイリスト"},"FumenData":{"FumenData":[{"FumenConstIntegerPart":"4","FumenConstFractionalPart":"0","FumenFile":{"path":"0931_00.ogkr"}},{"FumenConstIntegerPart":"7","FumenConstFractionalPart":"70","FumenFile":{"path":"0931_01.ogkr"}},{"FumenConstIntegerPart":"10","FumenConstFractionalPart":"40","FumenFile":{"path":"0931_02.ogkr"}},{"FumenConstIntegerPart":"12","FumenConstFractionalPart":"90","FumenFile":{"path":"0931_03.ogkr"}},{"FumenConstIntegerPart":"0","FumenConstFractionalPart":"0","FumenFile":{"path":null}}]},"IsLunatic":"false","BossCard":{"id":"100019","str":"【N】三角 葵"},"BossLevel":"21","WaveAttribute":{"AttributeType":"Aqua"},"CostToUnlock":"0","FinishBonus":"2","EpReleaseFlag":"false","VersionID":{"id":"1035","str":"ver_1_35"},"SortOrder":"500730","StageID":{"id":"3","str":"学園_03_旧校舎前"},"PossessingFromTheBeginning":"false","IsLockedAtTheBeginning":"true","ReleaseVersion":"2023-04-27T00:00:00","NameForSort":"ホシメクリハテノキミヘ","BossLockHpCoef":"0","BossLockRewards":null,"BossVoiceNo":"3","IsBonusTrack":"false"}