{"dataName":"Map100052","name":{"id":"100052","str":"ご注文はうさぎですか？？ちほー"},"IsCollabo":"true","IsInfinity":"false","IslandId":{"id":"10","str":"maimaiDX Splash"},"ReleaseConditionIds":{"list":null},"ColorId":{"id":"100052","str":"ごちうさ"},"BonusMusicId":{"id":"100052","str":"ご注文はうさぎですか？？ちほーボーナス曲"},"BonusMusicMagnification":"2000","OpenEventId":{"id":"20091742","str":"200917_04_2"},"netOpenName":{"id":"200917","str":"Net200917"},"TreasureExDatas":{"MapTreasureExData":[{"Distance":"0","Flag":"DispCharacter","SubParam1":"-1","SubParam2":"-1","TreasureId":{"id":"105201","str":"ココア"}},{"Distance":"18000","Flag":"DispCharacter","SubParam1":"-1","SubParam2":"-1","TreasureId":{"id":"105202","str":"チノ"}},{"Distance":"38000","Flag":"DispCharacter","SubParam1":"-1","SubParam2":"-1","TreasureId":{"id":"105203","str":"リゼ"}},{"Distance":"126000","Flag":"DispCharacter","SubParam1":"-1","SubParam2":"-1","TreasureId":{"id":"105251","str":"ご注文はうさぎですか？？ちほー"}},{"Distance":"159000","Flag":"DispCharacter","SubParam1":"-1","SubParam2":"-1","TreasureId":{"id":"105204","str":"千夜"}},{"Distance":"198000","Flag":"DispCharacter","SubParam1":"-1","SubParam2":"-1","TreasureId":{"id":"105205","str":"シャロ"}},{"Distance":"366000","Flag":"End","SubParam1":"-1","SubParam2":"-1","TreasureId":{"id":"105261","str":"ご注文はうさぎですか？？ちほー"}}]}}