{"dataName":"Map100060","name":{"id":"100060","str":"いらすとやちほー"},"IsCollabo":"true","IsInfinity":"false","IslandId":{"id":"10","str":"maimaiDX Splash"},"ReleaseConditionIds":{"list":null},"ColorId":{"id":"100060","str":"いらすとや"},"BonusMusicId":{"id":"100060","str":"いらすとやちほーボーナス曲"},"BonusMusicMagnification":"2000","OpenEventId":{"id":"20122542","str":"201225_04_2"},"netOpenName":{"id":"201225","str":"Net201225"},"TreasureExDatas":{"MapTreasureExData":[{"Distance":"0","Flag":"DispCharacter","SubParam1":"-1","SubParam2":"-1","TreasureId":{"id":"106001","str":"踊っているくまのイラスト"}},{"Distance":"18000","Flag":"DispCharacter","SubParam1":"-1","SubParam2":"-1","TreasureId":{"id":"106002","str":"踊っているいぬのイラスト"}},{"Distance":"48000","Flag":"DispCharacter","SubParam1":"-1","SubParam2":"-1","TreasureId":{"id":"106003","str":"踊っているねこのイラスト"}},{"Distance":"92000","Flag":"DispCharacter","SubParam1":"-1","SubParam2":"-1","TreasureId":{"id":"106004","str":"踊っているうさぎのイラスト"}},{"Distance":"170000","Flag":"DispCharacter","SubParam1":"-1","SubParam2":"-1","TreasureId":{"id":"106021","str":"Arty Party"}},{"Distance":"209000","Flag":"DispCharacter","SubParam1":"-1","SubParam2":"-1","TreasureId":{"id":"106005","str":"元気な男性のイラスト"}},{"Distance":"279000","Flag":"DispCharacter","SubParam1":"-1","SubParam2":"-1","TreasureId":{"id":"106006","str":"元気な女性のイラスト"}},{"Distance":"349000","Flag":"DispCharacter","SubParam1":"-1","SubParam2":"-1","TreasureId":{"id":"106007","str":"ドラム式洗濯機のイラスト"}},{"Distance":"461000","Flag":"DispCharacter","SubParam1":"-1","SubParam2":"-1","TreasureId":{"id":"106051","str":"いらすとやちほー"}},{"Distance":"503000","Flag":"DispCharacter","SubParam1":"-1","SubParam2":"-1","TreasureId":{"id":"106008","str":"コウテイペンギンのイラスト"}},{"Distance":"545000","Flag":"DispCharacter","SubParam1":"-1","SubParam2":"-1","TreasureId":{"id":"106009","str":"コウテイペンギンのヒナのイラスト"}},{"Distance":"671000","Flag":"DispCharacter","SubParam1":"-1","SubParam2":"-1","TreasureId":{"id":"106010","str":"バナナボートに乗る人たちのイラスト"}},{"Distance":"797000","Flag":"End","SubParam1":"-1","SubParam2":"-1","TreasureId":{"id":"106061","str":"いらすとやちほー"}}]}}