{"dataName":"course00020006","releaseTagName":{"id":"14","str":"v2 2.10.00","data":null},"netOpenName":{"id":"2300","str":"v2_15 00_0","data":null},"disableFlag":"false","name":{"id":"20006","str":"NEW!!リレイション Vocal","data":null},"difficulty":{"id":"11","str":"ID_11","data":"CLASS Ⅱ"},"rule":{"id":"32","str":"0032","data":null},"reward":{"id":"10000300","str":"Point 30000","data":null},"reward2nd":{"id":"0","str":"なし","data":null},"teamOnly":"false","isMusicDuplicateAllowed":"true","conditionsCourse":{"id":"-1","str":"Invalid","data":null},"conditionsText":null,"priority":"0","infos":{"CourseMusicDataInfo":[{"type":"0","selectMusic":{"musicName":{"id":"2055","str":"Ring","data":null},"musicDiff":{"id":"3","str":"Master","data":"MASTER"}},"selectLevel":{"fromLevel":{"id":"-1","str":"Invalid","data":null}},"selectMusicList":{"musicList":{"list":null},"panelType":"0","isRecordShown":"true"}},{"type":"0","selectMusic":{"musicName":{"id":"2062","str":"夢路拍子","data":null},"musicDiff":{"id":"3","str":"Master","data":"MASTER"}},"selectLevel":{"fromLevel":{"id":"-1","str":"Invalid","data":null}},"selectMusicList":{"musicList":{"list":null},"panelType":"0","isRecordShown":"true"}},{"type":"0","selectMusic":{"musicName":{"id":"2187","str":"タイムカプセル","data":null},"musicDiff":{"id":"3","str":"Master","data":"MASTER"}},"selectLevel":{"fromLevel":{"id":"-1","str":"Invalid","data":null}},"selectMusicList":{"musicList":{"list":null},"panelType":"0","isRecordShown":"true"}}]}}