{"dataName":"music000414","netOpenName":{"id":"0","str":"Net190711"},"releaseTagName":{"id":"1","str":"Ver1.00.00"},"disable":"false","name":{"id":"414","str":"若い力 -SEGA HARD GIRLS MIX-"},"rightsInfoName":{"id":"73","str":"セガ・ハード・ガールズ ©SEGA TVアニメ『Hi☆sCoool! セハガール』©SEGA/セハガガ学園理事会"},"sortName":"ワカイチカラSEGAHARDGIRLSMIX","artistName":{"id":"189","str":"SC-3000(シーさん)/CV.相沢 舞、SG-1000(せん)/CV.芹澤 優、SG-1000Ⅱ(せんつー)/CV.大空直美、ゲームギア(ムギ)/CV.田中美海、ロボピッチャ(ぴっちゃん)/CV.もものはるな「Hi☆sCoool! セハガール」 [アニメPV]"},"genreName":{"id":"101","str":"POPSアニメ"},"bpm":"162","version":"15006","AddVersion":{"id":"5","str":"ORANGEPLUS"},"movieName":{"id":"414","str":"若い力 -SEGA HARD GIRLS MIX-"},"cueName":{"id":"414","str":"若い力 -SEGA HARD GIRLS MIX-"},"dresscode":"false","eventName":{"id":"1","str":"無期限常時解放"},"eventName2":{"id":"0","str":"解放なし"},"subEventName":{"id":"1","str":"無期限常時解放"},"lockType":"0","subLockType":"0","dotNetListView":"true","notesData":{"Notes":[{"file":{"path":"000414_00.ma2"},"level":"5","levelDecimal":"0","notesDesigner":{"id":"999","str":"-"},"notesType":"0","musicLevelID":"5","maxNotes":"178","isEnable":"true"},{"file":{"path":"000414_01.ma2"},"level":"7","levelDecimal":"1","notesDesigner":{"id":"999","str":"-"},"notesType":"0","musicLevelID":"7","maxNotes":"340","isEnable":"true"},{"file":{"path":"000414_02.ma2"},"level":"10","levelDecimal":"0","notesDesigner":{"id":"3","str":"某S氏"},"notesType":"0","musicLevelID":"13","maxNotes":"383","isEnable":"true"},{"file":{"path":"000414_03.ma2"},"level":"12","levelDecimal":"7","notesDesigner":{"id":"4","str":"Jack"},"notesType":"0","musicLevelID":"18","maxNotes":"695","isEnable":"true"},{"file":{"path":"000414_04.ma2"},"level":"12","levelDecimal":"7","notesDesigner":{"id":"10","str":"チャン@DP皆伝"},"notesType":"0","musicLevelID":"18","maxNotes":"495","isEnable":"true"},{"file":{"path":"000414_05.ma2"},"level":"0","levelDecimal":"0","notesDesigner":{"id":"0","str":null},"notesType":"0","musicLevelID":"0","maxNotes":"0","isEnable":"false"}]},"utageKanjiName":null,"comment":null,"utagePlayStyle":"0","fixedOptions":{"FixedOption":[{"_fixedOptionName":null,"_fixedOptionValue":null},{"_fixedOptionName":null,"_fixedOptionValue":null},{"_fixedOptionName":null,"_fixedOptionValue":null},{"_fixedOptionName":null,"_fixedOptionValue":null}]},"jacketFile":null,"thumbnailName":null,"rightFile":null,"priority":"0"}