{"dataName":"music010602","netOpenName":{"id":"210916","str":"Net210916"},"releaseTagName":{"id":"2001","str":"Ver1.20.00"},"disable":"false","name":{"id":"10602","str":"taboo tears you up"},"rightsInfoName":{"id":"58","str":"©上海アリス幻樂団"},"sortName":"TABOOTEARSYOUUP","artistName":{"id":"178","str":"REDALiCE (HARDCORE TANO*C)"},"genreName":{"id":"103","str":"東方Project"},"bpm":"180","version":"22000","AddVersion":{"id":"17","str":"UNiVERSE"},"movieName":{"id":"602","str":"taboo tears you up"},"cueName":{"id":"602","str":"taboo tears you up"},"dresscode":"false","eventName":{"id":"1","str":"無期限常時解放"},"eventName2":{"id":"0","str":"解放なし"},"subEventName":{"id":"0","str":"解放なし"},"lockType":"0","subLockType":"1","dotNetListView":"true","notesData":{"Notes":[{"file":{"path":"010602_00.ma2"},"level":"3","levelDecimal":"0","notesDesigner":{"id":"0","str":null},"notesType":"0","musicLevelID":"3","maxNotes":"142","isEnable":"true"},{"file":{"path":"010602_01.ma2"},"level":"7","levelDecimal":"8","notesDesigner":{"id":"0","str":null},"notesType":"0","musicLevelID":"8","maxNotes":"373","isEnable":"true"},{"file":{"path":"010602_02.ma2"},"level":"10","levelDecimal":"8","notesDesigner":{"id":"2","str":"はっぴー"},"notesType":"0","musicLevelID":"14","maxNotes":"501","isEnable":"true"},{"file":{"path":"010602_03.ma2"},"level":"13","levelDecimal":"9","notesDesigner":{"id":"27","str":"サファ太"},"notesType":"0","musicLevelID":"20","maxNotes":"937","isEnable":"true"},{"file":{"path":"010602_04.ma2"},"level":"0","levelDecimal":"0","notesDesigner":{"id":"0","str":null},"notesType":"0","musicLevelID":"0","maxNotes":"0","isEnable":"false"},{"file":{"path":"010602_05.ma2"},"level":"0","levelDecimal":"0","notesDesigner":{"id":"0","str":null},"notesType":"0","musicLevelID":"0","maxNotes":"0","isEnable":"false"}]},"utageKanjiName":null,"comment":null,"utagePlayStyle":"0","fixedOptions":{"FixedOption":[{"_fixedOptionName":null,"_fixedOptionValue":null},{"_fixedOptionName":null,"_fixedOptionValue":null},{"_fixedOptionName":null,"_fixedOptionValue":null},{"_fixedOptionName":null,"_fixedOptionValue":null}]},"jacketFile":null,"thumbnailName":null,"rightFile":null,"priority":"0"}