{"dataName":"music011518","netOpenName":{"id":"230310","str":"Net230310"},"releaseTagName":{"id":"3001","str":"Ver1.30.00"},"disable":"false","name":{"id":"11518","str":"ボッカデラベリタ"},"rightsInfoName":{"id":"0","str":null},"sortName":"ホツカテラヘリタ","artistName":{"id":"829","str":"柊キライ"},"genreName":{"id":"102","str":"niconicoボーカロイド"},"bpm":"170","version":"23015","AddVersion":{"id":"19","str":"FESTiVAL"},"movieName":{"id":"1518","str":"ボッカデラベリタ"},"cueName":{"id":"1518","str":"ボッカデラベリタ"},"dresscode":"false","eventName":{"id":"1","str":"無期限常時解放"},"eventName2":{"id":"0","str":"解放なし"},"subEventName":{"id":"0","str":"解放なし"},"lockType":"0","subLockType":"1","dotNetListView":"true","notesData":{"Notes":[{"file":{"path":"011518_00.ma2"},"level":"3","levelDecimal":"0","notesDesigner":{"id":"0","str":null},"notesType":"0","musicLevelID":"3","maxNotes":"167","isEnable":"true"},{"file":{"path":"011518_01.ma2"},"level":"7","levelDecimal":"0","notesDesigner":{"id":"0","str":null},"notesType":"0","musicLevelID":"7","maxNotes":"344","isEnable":"true"},{"file":{"path":"011518_02.ma2"},"level":"10","levelDecimal":"0","notesDesigner":{"id":"84","str":"翠楼屋"},"notesType":"0","musicLevelID":"13","maxNotes":"539","isEnable":"true"},{"file":{"path":"011518_03.ma2"},"level":"13","levelDecimal":"1","notesDesigner":{"id":"72","str":"Redarrow"},"notesType":"0","musicLevelID":"19","maxNotes":"796","isEnable":"true"},{"file":{"path":"011518_04.ma2"},"level":"0","levelDecimal":"0","notesDesigner":{"id":"0","str":null},"notesType":"0","musicLevelID":"0","maxNotes":"0","isEnable":"false"},{"file":{"path":"011518_05.ma2"},"level":"0","levelDecimal":"0","notesDesigner":{"id":"0","str":null},"notesType":"0","musicLevelID":"0","maxNotes":"0","isEnable":"false"}]},"utageKanjiName":null,"comment":null,"utagePlayStyle":"0","fixedOptions":{"FixedOption":[{"_fixedOptionName":null,"_fixedOptionValue":null},{"_fixedOptionName":null,"_fixedOptionValue":null},{"_fixedOptionName":null,"_fixedOptionValue":null},{"_fixedOptionName":null,"_fixedOptionValue":null}]},"jacketFile":null,"thumbnailName":null,"rightFile":null,"priority":"0"}