{"dataName":"event00014106","netOpenName":{"id":"2420","str":"v2_20 13_1","data":null},"name":{"id":"14106","str":"【Ver2.20】MORE MORE JUMP！ 2 [24年01月1回目配信]  |クエストフラグ1","data":null},"text":null,"ddsBannerName":{"id":"-1","str":"Invalid","data":null},"periodDispType":"1","alwaysOpen":"false","teamOnly":"false","isKop":"false","priority":"0","substances":{"type":"8","flag":{"value":"0"},"information":{"informationType":"0","informationDispType":"0","mapFilterID":{"id":"-1","str":"Invalid","data":null},"courseNames":{"list":null},"text":null,"image":{"path":null},"movieName":{"id":"-1","str":"Invalid","data":null},"presentNames":{"list":null}},"map":{"tagText":null,"mapName":{"id":"-1","str":"Invalid","data":null},"musicNames":{"list":null}},"music":{"musicType":"0","musicNames":{"list":null}},"advertiseMovie":{"firstMovieName":{"id":"-1","str":"Invalid","data":null},"secondMovieName":{"id":"-1","str":"Invalid","data":null}},"recommendMusic":{"musicNames":{"list":null}},"release":{"value":"0"},"course":{"courseNames":{"list":null}},"quest":{"questNames":{"list":{"StringID":{"id":"2150","str":"25時、ナイトコードで。 2","data":null}}}},"duel":{"duelName":{"id":"-1","str":"Invalid","data":null}},"cmission":{"cmissionName":{"id":"-1","str":"Invalid","data":null}},"changeSurfBoardUI":{"value":"0"},"avatarAccessoryGacha":{"avatarAccessoryGachaName":{"id":"-1","str":"Invalid","data":null}},"rightsInfo":{"rightsNames":{"list":null}},"playRewardSet":{"playRewardSetName":{"id":"-1","str":"Invalid","data":null}},"dailyBonusPreset":{"dailyBonusPresetName":{"id":"-1","str":"Invalid","data":null}}}}